fast_json_pointer/__init__.py
fast_json_pointer/cli.py
fast_json_pointer/exceptions.py
fast_json_pointer/rfc6901_parser.py
fast_json_pointer-0.3.3.dist-info/entry_points.txt
fast_json_pointer-0.3.3.dist-info/METADATA
fast_json_pointer-0.3.3.dist-info/LICENSE
fast_json_pointer-0.3.3.dist-info/WHEEL
fast_json_pointer-0.3.3.dist-info/RECORD
