Metadata-Version: 2.1
Name: fast-json-pointer
Version: 0.3.3
Summary: Implements RFC 6901 JSON pointers, and json-schema draft relative pointer resolution.
Home-page: https://github.com/SlowAPI/py-json-pointer
Keywords: json,json-pointer,rfc,rfc 6901
Author: Tristan Sweeney
Author-email: sweeneytri@gmail.com
Requires-Python: >=3.11,<4.0
Classifier: Development Status :: 2 - Pre-Alpha
Classifier: Intended Audience :: Developers
Classifier: License :: OSI Approved :: GNU Lesser General Public License v3 (LGPLv3)
Classifier: Operating System :: OS Independent
Classifier: Programming Language :: Python :: 3
Classifier: Programming Language :: Python :: 3.11
Classifier: Topic :: Software Development :: Libraries :: Python Modules
Provides-Extra: cli
Requires-Dist: typer[all] (>=0.7.0,<0.8.0) ; extra == "cli"
Project-URL: Documentation, https://py-json-pointer.readthedocs.io/en/latest/
Project-URL: Repository, https://github.com/SlowAPI/py-json-pointer
